URAdime/URAdime.py
URAdime/__init__.py
uradime-0.1.9.dist-info/METADATA
uradime-0.1.9.dist-info/WHEEL
uradime-0.1.9.dist-info/entry_points.txt
uradime-0.1.9.dist-info/RECORD
