Metadata-Version: 2.3
Name: URAdime
Version: 0.1.9
Summary: Universal Read Analysis of DIMErs
Project-URL: Homepage, https://github.com/SemiQuant/URAdime
Project-URL: Bug Tracker, https://github.com/SemiQuant/URAdime/issues
Author-email: Jason D Limberis <Jason.Limberis@ucsf.edu>
License: MIT
Keywords: DNA,PCR,analysis,primers,sequencing
Classifier: License :: OSI Approved :: MIT License
Classifier: Operating System :: OS Independent
Classifier: Programming Language :: Python :: 3
Requires-Python: >=3.7
Requires-Dist: biopython
Requires-Dist: numpy
Requires-Dist: pandas
Requires-Dist: pysam
Requires-Dist: python-levenshtein
Requires-Dist: tqdm
